tscausalinference/__init__.py
tscausalinference/__version__.py
tscausalinference/bootstrap.py
tscausalinference/evaluators.py
tscausalinference/load_synth_data.py
tscausalinference/main.py
tscausalinference/plots.py
tscausalinference/regression.py
tscausalinference/seasonality.py
tscausalinference/sensitivity_regression.py
tscausalinference/summaries.py
tscausalinference/synth_regression.py
tscausalinference-0.2.0.9.dist-info/LICENSE
tscausalinference-0.2.0.9.dist-info/METADATA
tscausalinference-0.2.0.9.dist-info/WHEEL
tscausalinference-0.2.0.9.dist-info/top_level.txt
tscausalinference-0.2.0.9.dist-info/RECORD
