Metadata-Version: 2.1
Name: tscausalinference
Version: 0.2.0.9
Summary: Bootstrap random walk simulations methodoly applied on top of Facebook Prophet to analyse causal effects
Author: Carlos Trujillo
Author-email: carlangastr@gmail.com
Keywords: python,causalimpact,causal inference,marketing,prophet,bootstrap,monte carlo random walks
Classifier: Development Status :: 3 - Alpha
Classifier: Intended Audience :: Developers
Classifier: License :: OSI Approved :: MIT License
Classifier: Programming Language :: Python :: 3
License-File: LICENSE
Requires-Dist: numpy
Requires-Dist: pandas
Requires-Dist: scikit-learn
Requires-Dist: prophet
Requires-Dist: scipy
Requires-Dist: tabulate
Requires-Dist: statsmodels
Requires-Dist: seaborn
